embl_tools/__init__.py
embl_tools/_version.py
embl_tools/core/.ipynb_checkpoints_ui.py
embl_tools/core/Backtranambig_codon_table.xml
embl_tools/core/_module_template.py
embl_tools/core/_ui_base.py
embl_tools/core/clustalO_ui.py
embl_tools/core/dbfetch_ui.py
embl_tools/core/emboss_backtranambig_ui.py
embl_tools/core/emboss_backtranseq_ui.py
embl_tools/core/emboss_cpgplot_ui.py
embl_tools/core/emboss_dotmatcher_ui.py
embl_tools/core/emboss_dotpath_ui.py
embl_tools/core/emboss_dottup_ui.py
embl_tools/core/emboss_isochore_ui.py
embl_tools/core/emboss_matcher_ui.py
embl_tools/core/emboss_needle_ui.py
embl_tools/core/emboss_newcpgreport_ui.py
embl_tools/core/emboss_pepinfo_ui.py
embl_tools/core/emboss_pepstats_ui.py
embl_tools/core/emboss_pepwindow_ui.py
embl_tools/core/emboss_polydot_ui.py
embl_tools/core/emboss_seqret_ui.py
embl_tools/core/emboss_sixpack_ui.py
embl_tools/core/emboss_stretcher_ui.py
embl_tools/core/emboss_transeq_ui.py
embl_tools/core/emboss_water_ui.py
embl_tools/core/fasta_ui.py
embl_tools/core/fastm_ui.py
embl_tools/core/genewise_ui.py
embl_tools/core/hmmer3_hmmscan_ui.py
embl_tools/core/hmmer3_phmmer_ui.py
embl_tools/core/infernal_cmscan_ui.py
embl_tools/core/iprscan5_ui.py
embl_tools/core/kalign_ui.py
embl_tools/core/lalign_ui.py
embl_tools/core/mafft_ui.py
embl_tools/core/mapmi_ui.py
embl_tools/core/muscle_ui.py
embl_tools/core/mview_ui.py
embl_tools/core/ncbiBlast_databases.xml
embl_tools/core/ncbiBlast_ui.py
embl_tools/core/pfamscan_ui.py
embl_tools/core/phobius_ui.py
embl_tools/core/prank_ui.py
embl_tools/core/pratt_ui.py
embl_tools/core/promoterwise_ui.py
embl_tools/core/psiblast_ui.py
embl_tools/core/psisearch2_ui.py
embl_tools/core/psisearch_ui.py
embl_tools/core/radar_ui.py
embl_tools/core/saps_ui.py
embl_tools/core/seqcksum_ui.py
embl_tools/core/simple_phylogeny_ui.py
embl_tools/core/tcoffee_ui.py
embl_tools/core/wise2dba_ui.py
embl_tools/embl_client/clustalo.py
embl_tools/embl_client/dbfetch.py
embl_tools_jl-0.3.3.dist-info/LICENSE
embl_tools_jl-0.3.3.dist-info/METADATA
embl_tools_jl-0.3.3.dist-info/WHEEL
embl_tools_jl-0.3.3.dist-info/top_level.txt
embl_tools_jl-0.3.3.dist-info/RECORD
