Metadata-Version: 2.1
Name: embl-tools-jl
Version: 0.3.3
Summary: An extension adding Launcher shortcuts to JupyterLab for EMBL Tools
Home-page: https://github.com/nandor-poka/ebml-tools-jl
Author: Dr. Nándor Póka
Author-email: np@np-bio.info
Maintainer: Dr. Nandor Poka
License: BSD-3-Clause
Keywords: Jupyter,JupyterLab,EMBL,EMBL-Tools,Bioinformatics
Platform: Linux
Platform: Mac OS X
Platform: Windows
Classifier: License :: OSI Approved :: BSD License
Classifier: Programming Language :: Python
Classifier: Programming Language :: Python :: 3
Classifier: Programming Language :: Python :: 3.5
Classifier: Programming Language :: Python :: 3.6
Classifier: Programming Language :: Python :: 3.7
Classifier: Programming Language :: Python :: 3.8
Classifier: Framework :: Jupyter
Requires-Dist: jupyterlab (~=2.0)
